estintest/__init__.py
estintest/hello.py
estinnnn-0.0.13.dist-info/METADATA
estinnnn-0.0.13.dist-info/WHEEL
estinnnn-0.0.13.dist-info/top_level.txt
estinnnn-0.0.13.dist-info/RECORD
